slurm_helper_utils/__init__.py
slurm_helper_utils/console_helper.py
slurm_helper_utils/create_slurm_script.py
slurm_helper_utils/file_utils.py
slurm_helper_utils/validate_slurm_script.py
slurm_helper_utils/conf/config.yaml
slurm_helper_utils/conf/config_builder.yaml
slurm_helper_utils-0.2.0.data/scripts/make_executables_and_aliases.py
slurm_helper_utils-0.2.0.dist-info/AUTHORS.rst
slurm_helper_utils-0.2.0.dist-info/LICENSE
slurm_helper_utils-0.2.0.dist-info/METADATA
slurm_helper_utils-0.2.0.dist-info/WHEEL
slurm_helper_utils-0.2.0.dist-info/entry_points.txt
slurm_helper_utils-0.2.0.dist-info/top_level.txt
slurm_helper_utils-0.2.0.dist-info/RECORD
